swork_mound/__init__.py
swork_mound/converter.py
swork_mound/patch/__init__.py
swork_mound/patch/print_patch.py
swork_mound-0.0.2.dist-info/LICENSE
swork_mound-0.0.2.dist-info/METADATA
swork_mound-0.0.2.dist-info/WHEEL
swork_mound-0.0.2.dist-info/entry_points.txt
swork_mound-0.0.2.dist-info/top_level.txt
swork_mound-0.0.2.dist-info/RECORD
