Metadata-Version: 2.1
Name: swork-mound
Version: 0.0.2
Summary: 工具库
Home-page: https://github.com/Xlj997/swork-mound
Author: Linjie Xing
Author-email: jin.951107@gmail.com
Classifier: Programming Language :: Python :: 3
Classifier: License :: OSI Approved :: MIT License
Classifier: Operating System :: OS Independent
License-File: LICENSE
